[
    {
        "jmhVersion" : "1.37",
        "benchmark" : "org.hestiastore.benchmark.segmentindex.SegmentIndexMixedDrainBenchmark.partitionedIngestMixed",
        "mode" : "thrpt",
        "threads" : 20,
        "forks" : 1,
        "jvm" : "/usr/lib/jvm/temurin-21-jdk-amd64/bin/java",
        "jvmArgs" : [
        ],
        "jdkVersion" : "21.0.10",
        "vmName" : "OpenJDK 64-Bit Server VM",
        "vmVersion" : "21.0.10+7-LTS",
        "warmupIterations" : 2,
        "warmupTime" : "2 s",
        "warmupBatchSize" : 1,
        "measurementIterations" : 5,
        "measurementTime" : "2 s",
        "measurementBatchSize" : 1,
        "params" : {
            "hotKeySpace" : "256",
            "workloadMode" : "drainOnly"
        },
        "primaryMetric" : {
            "score" : 779724.4950958106,
            "scoreError" : 126244.36193682597,
            "scoreConfidence" : [
                653480.1331589846,
                905968.8570326366
            ],
            "scorePercentiles" : {
                "0.0" : 737366.9386014096,
                "50.0" : 779305.5327259956,
                "90.0" : 814314.8058552059,
                "95.0" : 814314.8058552059,
                "99.0" : 814314.8058552059,
                "99.9" : 814314.8058552059,
                "99.99" : 814314.8058552059,
                "99.999" : 814314.8058552059,
                "99.9999" : 814314.8058552059,
                "100.0" : 814314.8058552059
            },
            "scoreUnit" : "ops/s",
            "rawData" : [
                [
                    737366.9386014096,
                    779305.5327259956,
                    758567.2690288674,
                    809067.9292675751,
                    814314.8058552059
                ]
            ]
        },
        "secondaryMetrics" : {
            "getWorkload" : {
                "score" : 774378.5615933344,
                "scoreError" : 126278.74829343078,
                "scoreConfidence" : [
                    648099.8132999036,
                    900657.3098867652
                ],
                "scorePercentiles" : {
                    "0.0" : 731999.0413148478,
                    "50.0" : 773938.4066258307,
                    "90.0" : 808939.4423741454,
                    "95.0" : 808939.4423741454,
                    "99.0" : 808939.4423741454,
                    "99.9" : 808939.4423741454,
                    "99.99" : 808939.4423741454,
                    "99.999" : 808939.4423741454,
                    "99.9999" : 808939.4423741454,
                    "100.0" : 808939.4423741454
                },
                "scoreUnit" : "ops/s",
                "rawData" : [
                    [
                        731999.0413148478,
                        773938.4066258307,
                        753238.8099451128,
                        803777.1077067351,
                        808939.4423741454
                    ]
                ]
            },
            "putWorkload" : {
                "score" : 5345.933502476459,
                "scoreError" : 138.03818770068372,
                "scoreConfidence" : [
                    5207.895314775775,
                    5483.971690177143
                ],
                "scorePercentiles" : {
                    "0.0" : 5290.821560840208,
                    "50.0" : 5367.126100165002,
                    "90.0" : 5375.3634810603835,
                    "95.0" : 5375.3634810603835,
                    "99.0" : 5375.3634810603835,
                    "99.9" : 5375.3634810603835,
                    "99.99" : 5375.3634810603835,
                    "99.999" : 5375.3634810603835,
                    "99.9999" : 5375.3634810603835,
                    "100.0" : 5375.3634810603835
                },
                "scoreUnit" : "ops/s",
                "rawData" : [
                    [
                        5367.897286562057,
                        5367.126100165002,
                        5328.459083754644,
                        5290.821560840208,
                        5375.3634810603835
                    ]
                ]
            }
        }
    }
]


