[
    {
        "jmhVersion" : "1.37",
        "benchmark" : "org.hestiastore.benchmark.segmentindex.SegmentIndexMixedDrainBenchmark.partitionedIngestMixed",
        "mode" : "thrpt",
        "threads" : 20,
        "forks" : 1,
        "jvm" : "/usr/lib/jvm/temurin-21-jdk-amd64/bin/java",
        "jvmArgs" : [
        ],
        "jdkVersion" : "21.0.11",
        "vmName" : "OpenJDK 64-Bit Server VM",
        "vmVersion" : "21.0.11+10-LTS",
        "warmupIterations" : 1,
        "warmupTime" : "1 s",
        "warmupBatchSize" : 1,
        "measurementIterations" : 3,
        "measurementTime" : "1 s",
        "measurementBatchSize" : 1,
        "params" : {
            "hotKeySpace" : "256",
            "workloadMode" : "splitHeavy"
        },
        "primaryMetric" : {
            "score" : 198531.57977745295,
            "scoreError" : 1011951.4601734527,
            "scoreConfidence" : [
                -813419.8803959998,
                1210483.0399509056
            ],
            "scorePercentiles" : {
                "0.0" : 140787.24752974592,
                "50.0" : 203404.8771557765,
                "90.0" : 251402.61464683642,
                "95.0" : 251402.61464683642,
                "99.0" : 251402.61464683642,
                "99.9" : 251402.61464683642,
                "99.99" : 251402.61464683642,
                "99.999" : 251402.61464683642,
                "99.9999" : 251402.61464683642,
                "100.0" : 251402.61464683642
            },
            "scoreUnit" : "ops/s",
            "rawData" : [
                [
                    140787.24752974592,
                    203404.8771557765,
                    251402.61464683642
                ]
            ]
        },
        "secondaryMetrics" : {
            "getWorkload" : {
                "score" : 184119.8879828645,
                "scoreError" : 978386.288345681,
                "scoreConfidence" : [
                    -794266.4003628165,
                    1162506.1763285454
                ],
                "scorePercentiles" : {
                    "0.0" : 128211.40418258077,
                    "50.0" : 189015.21411401973,
                    "90.0" : 235133.0456519929,
                    "95.0" : 235133.0456519929,
                    "99.0" : 235133.0456519929,
                    "99.9" : 235133.0456519929,
                    "99.99" : 235133.0456519929,
                    "99.999" : 235133.0456519929,
                    "99.9999" : 235133.0456519929,
                    "100.0" : 235133.0456519929
                },
                "scoreUnit" : "ops/s",
                "rawData" : [
                    [
                        128211.40418258077,
                        189015.21411401973,
                        235133.0456519929
                    ]
                ]
            },
            "putWorkload" : {
                "score" : 14411.691794588485,
                "scoreError" : 33695.45069900278,
                "scoreConfidence" : [
                    -19283.758904414295,
                    48107.142493591266
                ],
                "scorePercentiles" : {
                    "0.0" : 12575.843347165162,
                    "50.0" : 14389.66304175677,
                    "90.0" : 16269.568994843525,
                    "95.0" : 16269.568994843525,
                    "99.0" : 16269.568994843525,
                    "99.9" : 16269.568994843525,
                    "99.99" : 16269.568994843525,
                    "99.999" : 16269.568994843525,
                    "99.9999" : 16269.568994843525,
                    "100.0" : 16269.568994843525
                },
                "scoreUnit" : "ops/s",
                "rawData" : [
                    [
                        12575.843347165162,
                        14389.66304175677,
                        16269.568994843525
                    ]
                ]
            }
        }
    }
]


