[
    {
        "jmhVersion" : "1.37",
        "benchmark" : "org.hestiastore.benchmark.segmentindex.SegmentIndexMixedDrainBenchmark.partitionedIngestMixed",
        "mode" : "thrpt",
        "threads" : 20,
        "forks" : 1,
        "jvm" : "/usr/lib/jvm/temurin-21-jdk-amd64/bin/java",
        "jvmArgs" : [
        ],
        "jdkVersion" : "21.0.11",
        "vmName" : "OpenJDK 64-Bit Server VM",
        "vmVersion" : "21.0.11+10-LTS",
        "warmupIterations" : 1,
        "warmupTime" : "1 s",
        "warmupBatchSize" : 1,
        "measurementIterations" : 3,
        "measurementTime" : "1 s",
        "measurementBatchSize" : 1,
        "params" : {
            "hotKeySpace" : "256",
            "workloadMode" : "drainOnly"
        },
        "primaryMetric" : {
            "score" : 280549.23895055376,
            "scoreError" : 289342.40064346103,
            "scoreConfidence" : [
                -8793.161692907277,
                569891.6395940147
            ],
            "scorePercentiles" : {
                "0.0" : 262756.99516255956,
                "50.0" : 285688.85199640103,
                "90.0" : 293201.8696927006,
                "95.0" : 293201.8696927006,
                "99.0" : 293201.8696927006,
                "99.9" : 293201.8696927006,
                "99.99" : 293201.8696927006,
                "99.999" : 293201.8696927006,
                "99.9999" : 293201.8696927006,
                "100.0" : 293201.8696927006
            },
            "scoreUnit" : "ops/s",
            "rawData" : [
                [
                    262756.99516255956,
                    293201.8696927006,
                    285688.85199640103
                ]
            ]
        },
        "secondaryMetrics" : {
            "getWorkload" : {
                "score" : 120556.49502326098,
                "scoreError" : 731635.0144499688,
                "scoreConfidence" : [
                    -611078.5194267079,
                    852191.5094732298
                ],
                "scorePercentiles" : {
                    "0.0" : 74718.62282982316,
                    "50.0" : 137779.07197364792,
                    "90.0" : 149171.79026631181,
                    "95.0" : 149171.79026631181,
                    "99.0" : 149171.79026631181,
                    "99.9" : 149171.79026631181,
                    "99.99" : 149171.79026631181,
                    "99.999" : 149171.79026631181,
                    "99.9999" : 149171.79026631181,
                    "100.0" : 149171.79026631181
                },
                "scoreUnit" : "ops/s",
                "rawData" : [
                    [
                        149171.79026631181,
                        137779.07197364792,
                        74718.62282982316
                    ]
                ]
            },
            "putWorkload" : {
                "score" : 159992.7439272928,
                "scoreError" : 891262.1584361943,
                "scoreConfidence" : [
                    -731269.4145089015,
                    1051254.902363487
                ],
                "scorePercentiles" : {
                    "0.0" : 113585.20489624776,
                    "50.0" : 155422.79771905276,
                    "90.0" : 210970.22916657786,
                    "95.0" : 210970.22916657786,
                    "99.0" : 210970.22916657786,
                    "99.9" : 210970.22916657786,
                    "99.99" : 210970.22916657786,
                    "99.999" : 210970.22916657786,
                    "99.9999" : 210970.22916657786,
                    "100.0" : 210970.22916657786
                },
                "scoreUnit" : "ops/s",
                "rawData" : [
                    [
                        113585.20489624776,
                        155422.79771905276,
                        210970.22916657786
                    ]
                ]
            }
        }
    }
]


