[
    {
        "jmhVersion" : "1.37",
        "benchmark" : "org.hestiastore.benchmark.segmentindex.SegmentIndexMixedDrainBenchmark.partitionedIngestMixed",
        "mode" : "thrpt",
        "threads" : 20,
        "forks" : 1,
        "jvm" : "/usr/lib/jvm/temurin-21-jdk-amd64/bin/java",
        "jvmArgs" : [
        ],
        "jdkVersion" : "21.0.10",
        "vmName" : "OpenJDK 64-Bit Server VM",
        "vmVersion" : "21.0.10+7-LTS",
        "warmupIterations" : 1,
        "warmupTime" : "1 s",
        "warmupBatchSize" : 1,
        "measurementIterations" : 3,
        "measurementTime" : "1 s",
        "measurementBatchSize" : 1,
        "params" : {
            "hotKeySpace" : "256",
            "workloadMode" : "splitHeavy"
        },
        "primaryMetric" : {
            "score" : 189444.11322621757,
            "scoreError" : 955252.5660439127,
            "scoreConfidence" : [
                -765808.4528176951,
                1144696.6792701301
            ],
            "scorePercentiles" : {
                "0.0" : 130911.086238293,
                "50.0" : 205593.9303368493,
                "90.0" : 231827.32310351043,
                "95.0" : 231827.32310351043,
                "99.0" : 231827.32310351043,
                "99.9" : 231827.32310351043,
                "99.99" : 231827.32310351043,
                "99.999" : 231827.32310351043,
                "99.9999" : 231827.32310351043,
                "100.0" : 231827.32310351043
            },
            "scoreUnit" : "ops/s",
            "rawData" : [
                [
                    130911.086238293,
                    205593.9303368493,
                    231827.32310351043
                ]
            ]
        },
        "secondaryMetrics" : {
            "getWorkload" : {
                "score" : 186658.11239741798,
                "scoreError" : 960430.7547431462,
                "scoreConfidence" : [
                    -773772.6423457282,
                    1147088.8671405641
                ],
                "scorePercentiles" : {
                    "0.0" : 127869.2378732743,
                    "50.0" : 202660.78569227623,
                    "90.0" : 229444.31362670343,
                    "95.0" : 229444.31362670343,
                    "99.0" : 229444.31362670343,
                    "99.9" : 229444.31362670343,
                    "99.99" : 229444.31362670343,
                    "99.999" : 229444.31362670343,
                    "99.9999" : 229444.31362670343,
                    "100.0" : 229444.31362670343
                },
                "scoreUnit" : "ops/s",
                "rawData" : [
                    [
                        127869.2378732743,
                        202660.78569227623,
                        229444.31362670343
                    ]
                ]
            },
            "putWorkload" : {
                "score" : 2786.000828799602,
                "scoreError" : 6443.822488224507,
                "scoreConfidence" : [
                    -3657.8216594249047,
                    9229.82331702411
                ],
                "scorePercentiles" : {
                    "0.0" : 2383.0094768070117,
                    "50.0" : 2933.1446445730953,
                    "90.0" : 3041.848365018698,
                    "95.0" : 3041.848365018698,
                    "99.0" : 3041.848365018698,
                    "99.9" : 3041.848365018698,
                    "99.99" : 3041.848365018698,
                    "99.999" : 3041.848365018698,
                    "99.9999" : 3041.848365018698,
                    "100.0" : 3041.848365018698
                },
                "scoreUnit" : "ops/s",
                "rawData" : [
                    [
                        3041.848365018698,
                        2933.1446445730953,
                        2383.0094768070117
                    ]
                ]
            }
        }
    }
]


