[
    {
        "jmhVersion" : "1.37",
        "benchmark" : "org.hestiastore.benchmark.segmentindex.SegmentIndexMixedDrainBenchmark.partitionedIngestMixed",
        "mode" : "thrpt",
        "threads" : 20,
        "forks" : 1,
        "jvm" : "/usr/lib/jvm/temurin-21-jdk-amd64/bin/java",
        "jvmArgs" : [
        ],
        "jdkVersion" : "21.0.11",
        "vmName" : "OpenJDK 64-Bit Server VM",
        "vmVersion" : "21.0.11+10-LTS",
        "warmupIterations" : 1,
        "warmupTime" : "1 s",
        "warmupBatchSize" : 1,
        "measurementIterations" : 3,
        "measurementTime" : "1 s",
        "measurementBatchSize" : 1,
        "params" : {
            "hotKeySpace" : "256",
            "workloadMode" : "drainOnly"
        },
        "primaryMetric" : {
            "score" : 286188.7848605703,
            "scoreError" : 247635.92248165997,
            "scoreConfidence" : [
                38552.8623789103,
                533824.7073422302
            ],
            "scorePercentiles" : {
                "0.0" : 276582.17429054296,
                "50.0" : 280266.80461539206,
                "90.0" : 301717.37567577575,
                "95.0" : 301717.37567577575,
                "99.0" : 301717.37567577575,
                "99.9" : 301717.37567577575,
                "99.99" : 301717.37567577575,
                "99.999" : 301717.37567577575,
                "99.9999" : 301717.37567577575,
                "100.0" : 301717.37567577575
            },
            "scoreUnit" : "ops/s",
            "rawData" : [
                [
                    280266.80461539206,
                    276582.17429054296,
                    301717.37567577575
                ]
            ]
        },
        "secondaryMetrics" : {
            "getWorkload" : {
                "score" : 150095.4371706374,
                "scoreError" : 858355.2496202252,
                "scoreConfidence" : [
                    -708259.8124495877,
                    1008450.6867908626
                ],
                "scorePercentiles" : {
                    "0.0" : 109205.82055627817,
                    "50.0" : 139561.6956169852,
                    "90.0" : 201518.79533864878,
                    "95.0" : 201518.79533864878,
                    "99.0" : 201518.79533864878,
                    "99.9" : 201518.79533864878,
                    "99.99" : 201518.79533864878,
                    "99.999" : 201518.79533864878,
                    "99.9999" : 201518.79533864878,
                    "100.0" : 201518.79533864878
                },
                "scoreUnit" : "ops/s",
                "rawData" : [
                    [
                        201518.79533864878,
                        139561.6956169852,
                        109205.82055627817
                    ]
                ]
            },
            "putWorkload" : {
                "score" : 136093.34768993285,
                "scoreError" : 1037838.6688804191,
                "scoreConfidence" : [
                    -901745.3211904862,
                    1173932.016570352
                ],
                "scorePercentiles" : {
                    "0.0" : 78748.00927674331,
                    "50.0" : 137020.47867355775,
                    "90.0" : 192511.5551194975,
                    "95.0" : 192511.5551194975,
                    "99.0" : 192511.5551194975,
                    "99.9" : 192511.5551194975,
                    "99.99" : 192511.5551194975,
                    "99.999" : 192511.5551194975,
                    "99.9999" : 192511.5551194975,
                    "100.0" : 192511.5551194975
                },
                "scoreUnit" : "ops/s",
                "rawData" : [
                    [
                        78748.00927674331,
                        137020.47867355775,
                        192511.5551194975
                    ]
                ]
            }
        }
    }
]


